unexceptional.pth
unexceptional/__init__.py
unexceptional-0.0.2.data/data/unexceptional.pth
unexceptional-0.0.2.dist-info/LICENSE
unexceptional-0.0.2.dist-info/METADATA
unexceptional-0.0.2.dist-info/WHEEL
unexceptional-0.0.2.dist-info/top_level.txt
unexceptional-0.0.2.dist-info/RECORD
