Metadata-Version: 2.1
Name: unexceptional
Version: 0.0.2
Summary: No exceptions
Home-page: https://github.com/aidaco/unexceptional
Author: Aidan Courtney
Author-email: aidanfc97@gmail.com
License: MIT
Requires-Python: >=3.6
License-File: LICENSE
